{
  "header": {
    "statut": 200,
    "message": "OK",
    "total": 20,
    "debut": 0,
    "nombre": 20
  },
  "unitesLegales": [
    {
      "siren": "799938246",
      "statutDiffusionUniteLegale": "O",
      "dateCreationUniteLegale": "2014-01-27",
      "sigleUniteLegale": null,
      "sexeUniteLegale": "F",
      "prenom1UniteLegale": "SUZIMAR",
      "prenom2UniteLegale": null,
      "prenom3UniteLegale": null,
      "prenom4UniteLegale": null,
      "prenomUsuelUniteLegale": "SUZIMAR",
      "pseudonymeUniteLegale": null,
      "identifiantAssociationUniteLegale": null,
      "trancheEffectifsUniteLegale": null,
      "anneeEffectifsUniteLegale": null,
      "dateDernierTraitementUniteLegale": "2017-04-13T00:30:47",
      "nombrePeriodesUniteLegale": 2,
      "categorieEntreprise": "PME",
      "anneeCategorieEntreprise": "2016",
      "periodesUniteLegale": [
        {
          "dateFin": null,
          "dateDebut": "2016-06-07",
          "etatAdministratifUniteLegale": "C",
          "changementEtatAdministratifUniteLegale": true,
          "nomUniteLegale": "BATISTA DE LIMA INC",
          "changementNomUniteLegale": false,
          "nomUsageUniteLegale": null,
          "changementNomUsageUniteLegale": false,
          "denominationUniteLegale": null,
          "changementDenominationUniteLegale": false,
          "denominationUsuelle1UniteLegale": null,
          "denominationUsuelle2UniteLegale": null,
          "denominationUsuelle3UniteLegale": null,
          "changementDenominationUsuelleUniteLegale": false,
          "categorieJuridiqueUniteLegale": "1000",
          "changementCategorieJuridiqueUniteLegale": false,
          "activitePrincipaleUniteLegale": "07.29Z",
          "nomenclatureActivitePrincipaleUniteLegale": "NAFRev2",
          "changementActivitePrincipaleUniteLegale": false,
          "nicSiegeUniteLegale": "00011",
          "changementNicSiegeUniteLegale": false,
          "economieSocialeSolidaireUniteLegale": null,
          "changementEconomieSocialeSolidaireUniteLegale": false,
          "caractereEmployeurUniteLegale": "N",
          "changementCaractereEmployeurUniteLegale": false
        },
        {
          "dateFin": "2016-06-06",
          "dateDebut": "2014-01-27",
          "etatAdministratifUniteLegale": "A",
          "changementEtatAdministratifUniteLegale": false,
          "nomUniteLegale": "BATISTA DE LIMA INC",
          "changementNomUniteLegale": false,
          "nomUsageUniteLegale": null,
          "changementNomUsageUniteLegale": false,
          "denominationUniteLegale": null,
          "changementDenominationUniteLegale": false,
          "denominationUsuelle1UniteLegale": null,
          "denominationUsuelle2UniteLegale": null,
          "denominationUsuelle3UniteLegale": null,
          "changementDenominationUsuelleUniteLegale": false,
          "categorieJuridiqueUniteLegale": "1000",
          "changementCategorieJuridiqueUniteLegale": false,
          "activitePrincipaleUniteLegale": "07.29Z",
          "nomenclatureActivitePrincipaleUniteLegale": "NAFRev2",
          "changementActivitePrincipaleUniteLegale": false,
          "nicSiegeUniteLegale": "00011",
          "changementNicSiegeUniteLegale": false,
          "economieSocialeSolidaireUniteLegale": null,
          "changementEconomieSocialeSolidaireUniteLegale": false,
          "caractereEmployeurUniteLegale": "N",
          "changementCaractereEmployeurUniteLegale": false
        }
      ]
    },
    {
      "siren": "813428315",
      "statutDiffusionUniteLegale": "O",
      "dateCreationUniteLegale": "2015-09-08",
      "sigleUniteLegale": null,
      "sexeUniteLegale": null,
      "prenom1UniteLegale": null,
      "prenom2UniteLegale": null,
      "prenom3UniteLegale": null,
      "prenom4UniteLegale": null,
      "prenomUsuelUniteLegale": null,
      "pseudonymeUniteLegale": null,
      "identifiantAssociationUniteLegale": null,
      "trancheEffectifsUniteLegale": "02",
      "anneeEffectifsUniteLegale": "2016",
      "dateDernierTraitementUniteLegale": "2018-09-29T13:55:28",
      "nombrePeriodesUniteLegale": 2,
      "categorieEntreprise": "PME",
      "anneeCategorieEntreprise": "2016",
      "periodesUniteLegale": [
        {
          "dateFin": null,
          "dateDebut": "2016-03-01",
          "etatAdministratifUniteLegale": "A",
          "changementEtatAdministratifUniteLegale": false,
          "nomUniteLegale": null,
          "changementNomUniteLegale": false,
          "nomUsageUniteLegale": null,
          "changementNomUsageUniteLegale": false,
          "denominationUniteLegale": "SOCIETE MINIERE DE REGINA SOMIREG",
          "changementDenominationUniteLegale": false,
          "denominationUsuelle1UniteLegale": null,
          "denominationUsuelle2UniteLegale": null,
          "denominationUsuelle3UniteLegale": null,
          "changementDenominationUsuelleUniteLegale": false,
          "categorieJuridiqueUniteLegale": "5499",
          "changementCategorieJuridiqueUniteLegale": false,
          "activitePrincipaleUniteLegale": "07.29Z",
          "nomenclatureActivitePrincipaleUniteLegale": "NAFRev2",
          "changementActivitePrincipaleUniteLegale": false,
          "nicSiegeUniteLegale": "00010",
          "changementNicSiegeUniteLegale": false,
          "economieSocialeSolidaireUniteLegale": null,
          "changementEconomieSocialeSolidaireUniteLegale": false,
          "caractereEmployeurUniteLegale": "O",
          "changementCaractereEmployeurUniteLegale": true
        },
        {
          "dateFin": "2016-02-29",
          "dateDebut": "2015-09-08",
          "etatAdministratifUniteLegale": "A",
          "changementEtatAdministratifUniteLegale": false,
          "nomUniteLegale": null,
          "changementNomUniteLegale": false,
          "nomUsageUniteLegale": null,
          "changementNomUsageUniteLegale": false,
          "denominationUniteLegale": "SOCIETE MINIERE DE REGINA SOMIREG",
          "changementDenominationUniteLegale": false,
          "denominationUsuelle1UniteLegale": null,
          "denominationUsuelle2UniteLegale": null,
          "denominationUsuelle3UniteLegale": null,
          "changementDenominationUsuelleUniteLegale": false,
          "categorieJuridiqueUniteLegale": "5499",
          "changementCategorieJuridiqueUniteLegale": false,
          "activitePrincipaleUniteLegale": "07.29Z",
          "nomenclatureActivitePrincipaleUniteLegale": "NAFRev2",
          "changementActivitePrincipaleUniteLegale": false,
          "nicSiegeUniteLegale": "00010",
          "changementNicSiegeUniteLegale": false,
          "economieSocialeSolidaireUniteLegale": null,
          "changementEconomieSocialeSolidaireUniteLegale": false,
          "caractereEmployeurUniteLegale": "N",
          "changementCaractereEmployeurUniteLegale": false
        }
      ]
    },
    {
      "siren": "811348432",
      "statutDiffusionUniteLegale": "O",
      "dateCreationUniteLegale": "2015-05-01",
      "sigleUniteLegale": "SOCARMINES",
      "sexeUniteLegale": null,
      "prenom1UniteLegale": null,
      "prenom2UniteLegale": null,
      "prenom3UniteLegale": null,
      "prenom4UniteLegale": null,
      "prenomUsuelUniteLegale": null,
      "pseudonymeUniteLegale": null,
      "identifiantAssociationUniteLegale": null,
      "trancheEffectifsUniteLegale": null,
      "anneeEffectifsUniteLegale": null,
      "dateDernierTraitementUniteLegale": "2017-05-20T04:48:21",
      "nombrePeriodesUniteLegale": 1,
      "categorieEntreprise": "PME",
      "anneeCategorieEntreprise": "2016",
      "periodesUniteLegale": [
        {
          "dateFin": null,
          "dateDebut": "2015-05-01",
          "etatAdministratifUniteLegale": "A",
          "changementEtatAdministratifUniteLegale": false,
          "nomUniteLegale": null,
          "changementNomUniteLegale": false,
          "nomUsageUniteLegale": null,
          "changementNomUsageUniteLegale": false,
          "denominationUniteLegale": "SOCIETE DE CARRIERE DE MINES",
          "changementDenominationUniteLegale": false,
          "denominationUsuelle1UniteLegale": null,
          "denominationUsuelle2UniteLegale": null,
          "denominationUsuelle3UniteLegale": null,
          "changementDenominationUsuelleUniteLegale": false,
          "categorieJuridiqueUniteLegale": "5499",
          "changementCategorieJuridiqueUniteLegale": false,
          "activitePrincipaleUniteLegale": "08.12Z",
          "nomenclatureActivitePrincipaleUniteLegale": "NAFRev2",
          "changementActivitePrincipaleUniteLegale": false,
          "nicSiegeUniteLegale": "00014",
          "changementNicSiegeUniteLegale": false,
          "economieSocialeSolidaireUniteLegale": null,
          "changementEconomieSocialeSolidaireUniteLegale": false,
          "caractereEmployeurUniteLegale": "N",
          "changementCaractereEmployeurUniteLegale": false
        }
      ]
    },
    {
      "siren": "811999044",
      "statutDiffusionUniteLegale": "O",
      "dateCreationUniteLegale": "2015-06-01",
      "sigleUniteLegale": null,
      "sexeUniteLegale": null,
      "prenom1UniteLegale": null,
      "prenom2UniteLegale": null,
      "prenom3UniteLegale": null,
      "prenom4UniteLegale": null,
      "prenomUsuelUniteLegale": null,
      "pseudonymeUniteLegale": null,
      "identifiantAssociationUniteLegale": null,
      "trancheEffectifsUniteLegale": null,
      "anneeEffectifsUniteLegale": null,
      "dateDernierTraitementUniteLegale": "2017-05-20T04:51:59",
      "nombrePeriodesUniteLegale": 1,
      "categorieEntreprise": "PME",
      "anneeCategorieEntreprise": "2016",
      "periodesUniteLegale": [
        {
          "dateFin": null,
          "dateDebut": "2015-06-01",
          "etatAdministratifUniteLegale": "A",
          "changementEtatAdministratifUniteLegale": false,
          "nomUniteLegale": null,
          "changementNomUniteLegale": false,
          "nomUsageUniteLegale": null,
          "changementNomUsageUniteLegale": false,
          "denominationUniteLegale": "EXALL 79",
          "changementDenominationUniteLegale": false,
          "denominationUsuelle1UniteLegale": null,
          "denominationUsuelle2UniteLegale": null,
          "denominationUsuelle3UniteLegale": null,
          "changementDenominationUsuelleUniteLegale": false,
          "categorieJuridiqueUniteLegale": "5710",
          "changementCategorieJuridiqueUniteLegale": false,
          "activitePrincipaleUniteLegale": "07.29Z",
          "nomenclatureActivitePrincipaleUniteLegale": "NAFRev2",
          "changementActivitePrincipaleUniteLegale": false,
          "nicSiegeUniteLegale": "00019",
          "changementNicSiegeUniteLegale": false,
          "economieSocialeSolidaireUniteLegale": null,
          "changementEconomieSocialeSolidaireUniteLegale": false,
          "caractereEmployeurUniteLegale": "N",
          "changementCaractereEmployeurUniteLegale": false
        }
      ]
    },
    {
      "siren": "811383462",
      "statutDiffusionUniteLegale": "O",
      "dateCreationUniteLegale": "2015-05-06",
      "sigleUniteLegale": null,
      "sexeUniteLegale": null,
      "prenom1UniteLegale": null,
      "prenom2UniteLegale": null,
      "prenom3UniteLegale": null,
      "prenom4UniteLegale": null,
      "prenomUsuelUniteLegale": null,
      "pseudonymeUniteLegale": null,
      "identifiantAssociationUniteLegale": null,
      "trancheEffectifsUniteLegale": null,
      "anneeEffectifsUniteLegale": null,
      "dateDernierTraitementUniteLegale": "2017-05-20T04:48:32",
      "nombrePeriodesUniteLegale": 1,
      "categorieEntreprise": "PME",
      "anneeCategorieEntreprise": "2016",
      "periodesUniteLegale": [
        {
          "dateFin": null,
          "dateDebut": "2015-05-06",
          "etatAdministratifUniteLegale": "A",
          "changementEtatAdministratifUniteLegale": false,
          "nomUniteLegale": null,
          "changementNomUniteLegale": false,
          "nomUsageUniteLegale": null,
          "changementNomUsageUniteLegale": false,
          "denominationUniteLegale": "SEMIR (SOCIETE EXPLOITATION MINIERE REUNIF)",
          "changementDenominationUniteLegale": false,
          "denominationUsuelle1UniteLegale": null,
          "denominationUsuelle2UniteLegale": null,
          "denominationUsuelle3UniteLegale": null,
          "changementDenominationUsuelleUniteLegale": false,
          "categorieJuridiqueUniteLegale": "5499",
          "changementCategorieJuridiqueUniteLegale": false,
          "activitePrincipaleUniteLegale": "07.29Z",
          "nomenclatureActivitePrincipaleUniteLegale": "NAFRev2",
          "changementActivitePrincipaleUniteLegale": false,
          "nicSiegeUniteLegale": "00017",
          "changementNicSiegeUniteLegale": false,
          "economieSocialeSolidaireUniteLegale": null,
          "changementEconomieSocialeSolidaireUniteLegale": false,
          "caractereEmployeurUniteLegale": "N",
          "changementCaractereEmployeurUniteLegale": false
        }
      ]
    },
    {
      "siren": "811348325",
      "statutDiffusionUniteLegale": "O",
      "dateCreationUniteLegale": "2015-01-01",
      "sigleUniteLegale": null,
      "sexeUniteLegale": null,
      "prenom1UniteLegale": null,
      "prenom2UniteLegale": null,
      "prenom3UniteLegale": null,
      "prenom4UniteLegale": null,
      "prenomUsuelUniteLegale": null,
      "pseudonymeUniteLegale": null,
      "identifiantAssociationUniteLegale": null,
      "trancheEffectifsUniteLegale": null,
      "anneeEffectifsUniteLegale": null,
      "dateDernierTraitementUniteLegale": "2018-08-10T04:09:42",
      "nombrePeriodesUniteLegale": 2,
      "categorieEntreprise": "PME",
      "anneeCategorieEntreprise": "2016",
      "periodesUniteLegale": [
        {
          "dateFin": null,
          "dateDebut": "2017-01-17",
          "etatAdministratifUniteLegale": "A",
          "changementEtatAdministratifUniteLegale": false,
          "nomUniteLegale": null,
          "changementNomUniteLegale": false,
          "nomUsageUniteLegale": null,
          "changementNomUsageUniteLegale": false,
          "denominationUniteLegale": "SOLEIL",
          "changementDenominationUniteLegale": false,
          "denominationUsuelle1UniteLegale": null,
          "denominationUsuelle2UniteLegale": null,
          "denominationUsuelle3UniteLegale": null,
          "changementDenominationUsuelleUniteLegale": false,
          "categorieJuridiqueUniteLegale": "5710",
          "changementCategorieJuridiqueUniteLegale": false,
          "activitePrincipaleUniteLegale": "07.29Z",
          "nomenclatureActivitePrincipaleUniteLegale": "NAFRev2",
          "changementActivitePrincipaleUniteLegale": false,
          "nicSiegeUniteLegale": "00010",
          "changementNicSiegeUniteLegale": false,
          "economieSocialeSolidaireUniteLegale": null,
          "changementEconomieSocialeSolidaireUniteLegale": false,
          "caractereEmployeurUniteLegale": "O",
          "changementCaractereEmployeurUniteLegale": true
        },
        {
          "dateFin": "2017-01-16",
          "dateDebut": "2015-01-01",
          "etatAdministratifUniteLegale": "A",
          "changementEtatAdministratifUniteLegale": false,
          "nomUniteLegale": null,
          "changementNomUniteLegale": false,
          "nomUsageUniteLegale": null,
          "changementNomUsageUniteLegale": false,
          "denominationUniteLegale": "SOLEIL",
          "changementDenominationUniteLegale": false,
          "denominationUsuelle1UniteLegale": null,
          "denominationUsuelle2UniteLegale": null,
          "denominationUsuelle3UniteLegale": null,
          "changementDenominationUsuelleUniteLegale": false,
          "categorieJuridiqueUniteLegale": "5710",
          "changementCategorieJuridiqueUniteLegale": false,
          "activitePrincipaleUniteLegale": "07.29Z",
          "nomenclatureActivitePrincipaleUniteLegale": "NAFRev2",
          "changementActivitePrincipaleUniteLegale": false,
          "nicSiegeUniteLegale": "00010",
          "changementNicSiegeUniteLegale": false,
          "economieSocialeSolidaireUniteLegale": null,
          "changementEconomieSocialeSolidaireUniteLegale": false,
          "caractereEmployeurUniteLegale": "N",
          "changementCaractereEmployeurUniteLegale": false
        }
      ]
    },
    {
      "siren": "804070423",
      "statutDiffusionUniteLegale": "O",
      "dateCreationUniteLegale": "2014-07-25",
      "sigleUniteLegale": null,
      "sexeUniteLegale": null,
      "prenom1UniteLegale": null,
      "prenom2UniteLegale": null,
      "prenom3UniteLegale": null,
      "prenom4UniteLegale": null,
      "prenomUsuelUniteLegale": null,
      "pseudonymeUniteLegale": null,
      "identifiantAssociationUniteLegale": null,
      "trancheEffectifsUniteLegale": null,
      "anneeEffectifsUniteLegale": null,
      "dateDernierTraitementUniteLegale": "2014-08-14T13:57:12",
      "nombrePeriodesUniteLegale": 1,
      "categorieEntreprise": null,
      "anneeCategorieEntreprise": null,
      "periodesUniteLegale": [
        {
          "dateFin": null,
          "dateDebut": "2014-07-25",
          "etatAdministratifUniteLegale": "A",
          "changementEtatAdministratifUniteLegale": false,
          "nomUniteLegale": null,
          "changementNomUniteLegale": false,
          "nomUsageUniteLegale": null,
          "changementNomUsageUniteLegale": false,
          "denominationUniteLegale": "GUYANE CORPORATION MINIERE",
          "changementDenominationUniteLegale": false,
          "denominationUsuelle1UniteLegale": null,
          "denominationUsuelle2UniteLegale": null,
          "denominationUsuelle3UniteLegale": null,
          "changementDenominationUsuelleUniteLegale": false,
          "categorieJuridiqueUniteLegale": "5498",
          "changementCategorieJuridiqueUniteLegale": false,
          "activitePrincipaleUniteLegale": "00.00Z",
          "nomenclatureActivitePrincipaleUniteLegale": "NAFRev2",
          "changementActivitePrincipaleUniteLegale": false,
          "nicSiegeUniteLegale": "00012",
          "changementNicSiegeUniteLegale": false,
          "economieSocialeSolidaireUniteLegale": null,
          "changementEconomieSocialeSolidaireUniteLegale": false,
          "caractereEmployeurUniteLegale": "N",
          "changementCaractereEmployeurUniteLegale": false
        }
      ]
    },
    {
      "siren": "810406157",
      "statutDiffusionUniteLegale": "O",
      "dateCreationUniteLegale": "2015-02-01",
      "sigleUniteLegale": null,
      "sexeUniteLegale": null,
      "prenom1UniteLegale": null,
      "prenom2UniteLegale": null,
      "prenom3UniteLegale": null,
      "prenom4UniteLegale": null,
      "prenomUsuelUniteLegale": null,
      "pseudonymeUniteLegale": null,
      "identifiantAssociationUniteLegale": null,
      "trancheEffectifsUniteLegale": null,
      "anneeEffectifsUniteLegale": null,
      "dateDernierTraitementUniteLegale": "2017-05-20T04:43:10",
      "nombrePeriodesUniteLegale": 1,
      "categorieEntreprise": "PME",
      "anneeCategorieEntreprise": "2016",
      "periodesUniteLegale": [
        {
          "dateFin": null,
          "dateDebut": "2015-02-01",
          "etatAdministratifUniteLegale": "A",
          "changementEtatAdministratifUniteLegale": false,
          "nomUniteLegale": null,
          "changementNomUniteLegale": false,
          "nomUsageUniteLegale": null,
          "changementNomUsageUniteLegale": false,
          "denominationUniteLegale": "OROGUY",
          "changementDenominationUniteLegale": false,
          "denominationUsuelle1UniteLegale": null,
          "denominationUsuelle2UniteLegale": null,
          "denominationUsuelle3UniteLegale": null,
          "changementDenominationUsuelleUniteLegale": false,
          "categorieJuridiqueUniteLegale": "5720",
          "changementCategorieJuridiqueUniteLegale": false,
          "activitePrincipaleUniteLegale": "07.29Z",
          "nomenclatureActivitePrincipaleUniteLegale": "NAFRev2",
          "changementActivitePrincipaleUniteLegale": false,
          "nicSiegeUniteLegale": "00018",
          "changementNicSiegeUniteLegale": false,
          "economieSocialeSolidaireUniteLegale": null,
          "changementEconomieSocialeSolidaireUniteLegale": false,
          "caractereEmployeurUniteLegale": "N",
          "changementCaractereEmployeurUniteLegale": false
        }
      ]
    },
    {
      "siren": "803975135",
      "statutDiffusionUniteLegale": "O",
      "dateCreationUniteLegale": "2014-08-01",
      "sigleUniteLegale": null,
      "sexeUniteLegale": null,
      "prenom1UniteLegale": null,
      "prenom2UniteLegale": null,
      "prenom3UniteLegale": null,
      "prenom4UniteLegale": null,
      "prenomUsuelUniteLegale": null,
      "pseudonymeUniteLegale": null,
      "identifiantAssociationUniteLegale": null,
      "trancheEffectifsUniteLegale": null,
      "anneeEffectifsUniteLegale": null,
      "dateDernierTraitementUniteLegale": "2018-01-30T15:22:59",
      "nombrePeriodesUniteLegale": 2,
      "categorieEntreprise": "PME",
      "anneeCategorieEntreprise": "2016",
      "periodesUniteLegale": [
        {
          "dateFin": null,
          "dateDebut": "2016-03-01",
          "etatAdministratifUniteLegale": "A",
          "changementEtatAdministratifUniteLegale": false,
          "nomUniteLegale": null,
          "changementNomUniteLegale": false,
          "nomUsageUniteLegale": null,
          "changementNomUsageUniteLegale": false,
          "denominationUniteLegale": "CORDIER MINES",
          "changementDenominationUniteLegale": false,
          "denominationUsuelle1UniteLegale": null,
          "denominationUsuelle2UniteLegale": null,
          "denominationUsuelle3UniteLegale": null,
          "changementDenominationUsuelleUniteLegale": false,
          "categorieJuridiqueUniteLegale": "5720",
          "changementCategorieJuridiqueUniteLegale": false,
          "activitePrincipaleUniteLegale": "09.90Z",
          "nomenclatureActivitePrincipaleUniteLegale": "NAFRev2",
          "changementActivitePrincipaleUniteLegale": false,
          "nicSiegeUniteLegale": "00028",
          "changementNicSiegeUniteLegale": true,
          "economieSocialeSolidaireUniteLegale": "N",
          "changementEconomieSocialeSolidaireUniteLegale": true,
          "caractereEmployeurUniteLegale": "N",
          "changementCaractereEmployeurUniteLegale": false
        },
        {
          "dateFin": "2016-02-29",
          "dateDebut": "2014-08-01",
          "etatAdministratifUniteLegale": "A",
          "changementEtatAdministratifUniteLegale": false,
          "nomUniteLegale": null,
          "changementNomUniteLegale": false,
          "nomUsageUniteLegale": null,
          "changementNomUsageUniteLegale": false,
          "denominationUniteLegale": "CORDIER MINES",
          "changementDenominationUniteLegale": false,
          "denominationUsuelle1UniteLegale": null,
          "denominationUsuelle2UniteLegale": null,
          "denominationUsuelle3UniteLegale": null,
          "changementDenominationUsuelleUniteLegale": false,
          "categorieJuridiqueUniteLegale": "5720",
          "changementCategorieJuridiqueUniteLegale": false,
          "activitePrincipaleUniteLegale": "09.90Z",
          "nomenclatureActivitePrincipaleUniteLegale": "NAFRev2",
          "changementActivitePrincipaleUniteLegale": false,
          "nicSiegeUniteLegale": "00010",
          "changementNicSiegeUniteLegale": false,
          "economieSocialeSolidaireUniteLegale": null,
          "changementEconomieSocialeSolidaireUniteLegale": false,
          "caractereEmployeurUniteLegale": "N",
          "changementCaractereEmployeurUniteLegale": false
        }
      ]
    },
    {
      "siren": "811636448",
      "statutDiffusionUniteLegale": "O",
      "dateCreationUniteLegale": "2015-04-10",
      "sigleUniteLegale": null,
      "sexeUniteLegale": null,
      "prenom1UniteLegale": null,
      "prenom2UniteLegale": null,
      "prenom3UniteLegale": null,
      "prenom4UniteLegale": null,
      "prenomUsuelUniteLegale": null,
      "pseudonymeUniteLegale": null,
      "identifiantAssociationUniteLegale": null,
      "trancheEffectifsUniteLegale": "00",
      "anneeEffectifsUniteLegale": "2016",
      "dateDernierTraitementUniteLegale": "2018-09-29T13:52:47",
      "nombrePeriodesUniteLegale": 4,
      "categorieEntreprise": "PME",
      "anneeCategorieEntreprise": "2016",
      "periodesUniteLegale": [
        {
          "dateFin": null,
          "dateDebut": "2016-05-17",
          "etatAdministratifUniteLegale": "A",
          "changementEtatAdministratifUniteLegale": false,
          "nomUniteLegale": null,
          "changementNomUniteLegale": false,
          "nomUsageUniteLegale": null,
          "changementNomUsageUniteLegale": false,
          "denominationUniteLegale": "AU FORAGES",
          "changementDenominationUniteLegale": false,
          "denominationUsuelle1UniteLegale": null,
          "denominationUsuelle2UniteLegale": null,
          "denominationUsuelle3UniteLegale": null,
          "changementDenominationUsuelleUniteLegale": false,
          "categorieJuridiqueUniteLegale": "5710",
          "changementCategorieJuridiqueUniteLegale": false,
          "activitePrincipaleUniteLegale": "09.90Z",
          "nomenclatureActivitePrincipaleUniteLegale": "NAFRev2",
          "changementActivitePrincipaleUniteLegale": false,
          "nicSiegeUniteLegale": "00029",
          "changementNicSiegeUniteLegale": true,
          "economieSocialeSolidaireUniteLegale": null,
          "changementEconomieSocialeSolidaireUniteLegale": false,
          "caractereEmployeurUniteLegale": "N",
          "changementCaractereEmployeurUniteLegale": false
        },
        {
          "dateFin": "2016-05-16",
          "dateDebut": "2016-05-16",
          "etatAdministratifUniteLegale": "A",
          "changementEtatAdministratifUniteLegale": false,
          "nomUniteLegale": null,
          "changementNomUniteLegale": false,
          "nomUsageUniteLegale": null,
          "changementNomUsageUniteLegale": false,
          "denominationUniteLegale": "AU FORAGES",
          "changementDenominationUniteLegale": false,
          "denominationUsuelle1UniteLegale": null,
          "denominationUsuelle2UniteLegale": null,
          "denominationUsuelle3UniteLegale": null,
          "changementDenominationUsuelleUniteLegale": false,
          "categorieJuridiqueUniteLegale": "5710",
          "changementCategorieJuridiqueUniteLegale": false,
          "activitePrincipaleUniteLegale": "09.90Z",
          "nomenclatureActivitePrincipaleUniteLegale": "NAFRev2",
          "changementActivitePrincipaleUniteLegale": false,
          "nicSiegeUniteLegale": "00011",
          "changementNicSiegeUniteLegale": false,
          "economieSocialeSolidaireUniteLegale": null,
          "changementEconomieSocialeSolidaireUniteLegale": false,
          "caractereEmployeurUniteLegale": "N",
          "changementCaractereEmployeurUniteLegale": true
        },
        {
          "dateFin": "2016-05-15",
          "dateDebut": "2016-04-16",
          "etatAdministratifUniteLegale": "A",
          "changementEtatAdministratifUniteLegale": false,
          "nomUniteLegale": null,
          "changementNomUniteLegale": false,
          "nomUsageUniteLegale": null,
          "changementNomUsageUniteLegale": false,
          "denominationUniteLegale": "AU FORAGES",
          "changementDenominationUniteLegale": false,
          "denominationUsuelle1UniteLegale": null,
          "denominationUsuelle2UniteLegale": null,
          "denominationUsuelle3UniteLegale": null,
          "changementDenominationUsuelleUniteLegale": false,
          "categorieJuridiqueUniteLegale": "5710",
          "changementCategorieJuridiqueUniteLegale": true,
          "activitePrincipaleUniteLegale": "09.90Z",
          "nomenclatureActivitePrincipaleUniteLegale": "NAFRev2",
          "changementActivitePrincipaleUniteLegale": false,
          "nicSiegeUniteLegale": "00011",
          "changementNicSiegeUniteLegale": false,
          "economieSocialeSolidaireUniteLegale": null,
          "changementEconomieSocialeSolidaireUniteLegale": false,
          "caractereEmployeurUniteLegale": "O",
          "changementCaractereEmployeurUniteLegale": false
        },
        {
          "dateFin": "2016-04-15",
          "dateDebut": "2015-04-10",
          "etatAdministratifUniteLegale": "A",
          "changementEtatAdministratifUniteLegale": false,
          "nomUniteLegale": null,
          "changementNomUniteLegale": false,
          "nomUsageUniteLegale": null,
          "changementNomUsageUniteLegale": false,
          "denominationUniteLegale": "AU FORAGES",
          "changementDenominationUniteLegale": false,
          "denominationUsuelle1UniteLegale": null,
          "denominationUsuelle2UniteLegale": null,
          "denominationUsuelle3UniteLegale": null,
          "changementDenominationUsuelleUniteLegale": false,
          "categorieJuridiqueUniteLegale": "5720",
          "changementCategorieJuridiqueUniteLegale": false,
          "activitePrincipaleUniteLegale": "09.90Z",
          "nomenclatureActivitePrincipaleUniteLegale": "NAFRev2",
          "changementActivitePrincipaleUniteLegale": false,
          "nicSiegeUniteLegale": "00011",
          "changementNicSiegeUniteLegale": false,
          "economieSocialeSolidaireUniteLegale": null,
          "changementEconomieSocialeSolidaireUniteLegale": false,
          "caractereEmployeurUniteLegale": "O",
          "changementCaractereEmployeurUniteLegale": false
        }
      ]
    },
    {
      "siren": "807407630",
      "statutDiffusionUniteLegale": "O",
      "dateCreationUniteLegale": "2014-10-23",
      "sigleUniteLegale": null,
      "sexeUniteLegale": null,
      "prenom1UniteLegale": null,
      "prenom2UniteLegale": null,
      "prenom3UniteLegale": null,
      "prenom4UniteLegale": null,
      "prenomUsuelUniteLegale": null,
      "pseudonymeUniteLegale": null,
      "identifiantAssociationUniteLegale": null,
      "trancheEffectifsUniteLegale": null,
      "anneeEffectifsUniteLegale": null,
      "dateDernierTraitementUniteLegale": "2018-02-14T15:15:16",
      "nombrePeriodesUniteLegale": 2,
      "categorieEntreprise": "PME",
      "anneeCategorieEntreprise": "2016",
      "periodesUniteLegale": [
        {
          "dateFin": null,
          "dateDebut": "2017-05-03",
          "etatAdministratifUniteLegale": "A",
          "changementEtatAdministratifUniteLegale": false,
          "nomUniteLegale": null,
          "changementNomUniteLegale": false,
          "nomUsageUniteLegale": null,
          "changementNomUsageUniteLegale": false,
          "denominationUniteLegale": "GROUPE AL MACTOUM",
          "changementDenominationUniteLegale": false,
          "denominationUsuelle1UniteLegale": null,
          "denominationUsuelle2UniteLegale": null,
          "denominationUsuelle3UniteLegale": null,
          "changementDenominationUsuelleUniteLegale": false,
          "categorieJuridiqueUniteLegale": "5710",
          "changementCategorieJuridiqueUniteLegale": false,
          "activitePrincipaleUniteLegale": "07.29Z",
          "nomenclatureActivitePrincipaleUniteLegale": "NAFRev2",
          "changementActivitePrincipaleUniteLegale": false,
          "nicSiegeUniteLegale": "00019",
          "changementNicSiegeUniteLegale": false,
          "economieSocialeSolidaireUniteLegale": null,
          "changementEconomieSocialeSolidaireUniteLegale": false,
          "caractereEmployeurUniteLegale": "O",
          "changementCaractereEmployeurUniteLegale": true
        },
        {
          "dateFin": "2017-05-02",
          "dateDebut": "2014-10-23",
          "etatAdministratifUniteLegale": "A",
          "changementEtatAdministratifUniteLegale": false,
          "nomUniteLegale": null,
          "changementNomUniteLegale": false,
          "nomUsageUniteLegale": null,
          "changementNomUsageUniteLegale": false,
          "denominationUniteLegale": "GROUPE AL MACTOUM",
          "changementDenominationUniteLegale": false,
          "denominationUsuelle1UniteLegale": null,
          "denominationUsuelle2UniteLegale": null,
          "denominationUsuelle3UniteLegale": null,
          "changementDenominationUsuelleUniteLegale": false,
          "categorieJuridiqueUniteLegale": "5710",
          "changementCategorieJuridiqueUniteLegale": false,
          "activitePrincipaleUniteLegale": "07.29Z",
          "nomenclatureActivitePrincipaleUniteLegale": "NAFRev2",
          "changementActivitePrincipaleUniteLegale": false,
          "nicSiegeUniteLegale": "00019",
          "changementNicSiegeUniteLegale": false,
          "economieSocialeSolidaireUniteLegale": null,
          "changementEconomieSocialeSolidaireUniteLegale": false,
          "caractereEmployeurUniteLegale": "N",
          "changementCaractereEmployeurUniteLegale": false
        }
      ]
    },
    {
      "siren": "809831027",
      "statutDiffusionUniteLegale": "O",
      "dateCreationUniteLegale": "2015-02-24",
      "sigleUniteLegale": null,
      "sexeUniteLegale": "M",
      "prenom1UniteLegale": "SYLVESTRE",
      "prenom2UniteLegale": null,
      "prenom3UniteLegale": null,
      "prenom4UniteLegale": null,
      "prenomUsuelUniteLegale": "SYLVESTRE",
      "pseudonymeUniteLegale": null,
      "identifiantAssociationUniteLegale": null,
      "trancheEffectifsUniteLegale": null,
      "anneeEffectifsUniteLegale": null,
      "dateDernierTraitementUniteLegale": "2018-01-30T11:47:14",
      "nombrePeriodesUniteLegale": 2,
      "categorieEntreprise": "PME",
      "anneeCategorieEntreprise": "2016",
      "periodesUniteLegale": [
        {
          "dateFin": null,
          "dateDebut": "2018-01-29",
          "etatAdministratifUniteLegale": "C",
          "changementEtatAdministratifUniteLegale": true,
          "nomUniteLegale": "PRALIER",
          "changementNomUniteLegale": false,
          "nomUsageUniteLegale": null,
          "changementNomUsageUniteLegale": false,
          "denominationUniteLegale": null,
          "changementDenominationUniteLegale": false,
          "denominationUsuelle1UniteLegale": null,
          "denominationUsuelle2UniteLegale": null,
          "denominationUsuelle3UniteLegale": null,
          "changementDenominationUsuelleUniteLegale": false,
          "categorieJuridiqueUniteLegale": "1000",
          "changementCategorieJuridiqueUniteLegale": false,
          "activitePrincipaleUniteLegale": "07.29Z",
          "nomenclatureActivitePrincipaleUniteLegale": "NAFRev2",
          "changementActivitePrincipaleUniteLegale": false,
          "nicSiegeUniteLegale": "00010",
          "changementNicSiegeUniteLegale": false,
          "economieSocialeSolidaireUniteLegale": null,
          "changementEconomieSocialeSolidaireUniteLegale": false,
          "caractereEmployeurUniteLegale": "N",
          "changementCaractereEmployeurUniteLegale": false
        },
        {
          "dateFin": "2018-01-28",
          "dateDebut": "2015-02-24",
          "etatAdministratifUniteLegale": "A",
          "changementEtatAdministratifUniteLegale": false,
          "nomUniteLegale": "PRALIER",
          "changementNomUniteLegale": false,
          "nomUsageUniteLegale": null,
          "changementNomUsageUniteLegale": false,
          "denominationUniteLegale": null,
          "changementDenominationUniteLegale": false,
          "denominationUsuelle1UniteLegale": null,
          "denominationUsuelle2UniteLegale": null,
          "denominationUsuelle3UniteLegale": null,
          "changementDenominationUsuelleUniteLegale": false,
          "categorieJuridiqueUniteLegale": "1000",
          "changementCategorieJuridiqueUniteLegale": false,
          "activitePrincipaleUniteLegale": "07.29Z",
          "nomenclatureActivitePrincipaleUniteLegale": "NAFRev2",
          "changementActivitePrincipaleUniteLegale": false,
          "nicSiegeUniteLegale": "00010",
          "changementNicSiegeUniteLegale": false,
          "economieSocialeSolidaireUniteLegale": null,
          "changementEconomieSocialeSolidaireUniteLegale": false,
          "caractereEmployeurUniteLegale": "N",
          "changementCaractereEmployeurUniteLegale": false
        }
      ]
    },
    {
      "siren": "810011601",
      "statutDiffusionUniteLegale": "O",
      "dateCreationUniteLegale": "2015-03-04",
      "sigleUniteLegale": null,
      "sexeUniteLegale": null,
      "prenom1UniteLegale": null,
      "prenom2UniteLegale": null,
      "prenom3UniteLegale": null,
      "prenom4UniteLegale": null,
      "prenomUsuelUniteLegale": null,
      "pseudonymeUniteLegale": null,
      "identifiantAssociationUniteLegale": null,
      "trancheEffectifsUniteLegale": "01",
      "anneeEffectifsUniteLegale": "2016",
      "dateDernierTraitementUniteLegale": "2018-09-29T13:50:22",
      "nombrePeriodesUniteLegale": 3,
      "categorieEntreprise": "PME",
      "anneeCategorieEntreprise": "2016",
      "periodesUniteLegale": [
        {
          "dateFin": null,
          "dateDebut": "2018-03-26",
          "etatAdministratifUniteLegale": "A",
          "changementEtatAdministratifUniteLegale": false,
          "nomUniteLegale": null,
          "changementNomUniteLegale": false,
          "nomUsageUniteLegale": null,
          "changementNomUsageUniteLegale": false,
          "denominationUniteLegale": "MIMI MINE",
          "changementDenominationUniteLegale": false,
          "denominationUsuelle1UniteLegale": null,
          "denominationUsuelle2UniteLegale": null,
          "denominationUsuelle3UniteLegale": null,
          "changementDenominationUsuelleUniteLegale": false,
          "categorieJuridiqueUniteLegale": "5499",
          "changementCategorieJuridiqueUniteLegale": false,
          "activitePrincipaleUniteLegale": "07.29Z",
          "nomenclatureActivitePrincipaleUniteLegale": "NAFRev2",
          "changementActivitePrincipaleUniteLegale": false,
          "nicSiegeUniteLegale": "00012",
          "changementNicSiegeUniteLegale": false,
          "economieSocialeSolidaireUniteLegale": null,
          "changementEconomieSocialeSolidaireUniteLegale": false,
          "caractereEmployeurUniteLegale": "N",
          "changementCaractereEmployeurUniteLegale": true
        },
        {
          "dateFin": "2018-03-25",
          "dateDebut": "2016-09-02",
          "etatAdministratifUniteLegale": "A",
          "changementEtatAdministratifUniteLegale": false,
          "nomUniteLegale": null,
          "changementNomUniteLegale": false,
          "nomUsageUniteLegale": null,
          "changementNomUsageUniteLegale": false,
          "denominationUniteLegale": "MIMI MINE",
          "changementDenominationUniteLegale": false,
          "denominationUsuelle1UniteLegale": null,
          "denominationUsuelle2UniteLegale": null,
          "denominationUsuelle3UniteLegale": null,
          "changementDenominationUsuelleUniteLegale": false,
          "categorieJuridiqueUniteLegale": "5499",
          "changementCategorieJuridiqueUniteLegale": false,
          "activitePrincipaleUniteLegale": "07.29Z",
          "nomenclatureActivitePrincipaleUniteLegale": "NAFRev2",
          "changementActivitePrincipaleUniteLegale": false,
          "nicSiegeUniteLegale": "00012",
          "changementNicSiegeUniteLegale": false,
          "economieSocialeSolidaireUniteLegale": null,
          "changementEconomieSocialeSolidaireUniteLegale": false,
          "caractereEmployeurUniteLegale": "O",
          "changementCaractereEmployeurUniteLegale": true
        },
        {
          "dateFin": "2016-09-01",
          "dateDebut": "2015-03-04",
          "etatAdministratifUniteLegale": "A",
          "changementEtatAdministratifUniteLegale": false,
          "nomUniteLegale": null,
          "changementNomUniteLegale": false,
          "nomUsageUniteLegale": null,
          "changementNomUsageUniteLegale": false,
          "denominationUniteLegale": "MIMI MINE",
          "changementDenominationUniteLegale": false,
          "denominationUsuelle1UniteLegale": null,
          "denominationUsuelle2UniteLegale": null,
          "denominationUsuelle3UniteLegale": null,
          "changementDenominationUsuelleUniteLegale": false,
          "categorieJuridiqueUniteLegale": "5499",
          "changementCategorieJuridiqueUniteLegale": false,
          "activitePrincipaleUniteLegale": "07.29Z",
          "nomenclatureActivitePrincipaleUniteLegale": "NAFRev2",
          "changementActivitePrincipaleUniteLegale": false,
          "nicSiegeUniteLegale": "00012",
          "changementNicSiegeUniteLegale": false,
          "economieSocialeSolidaireUniteLegale": null,
          "changementEconomieSocialeSolidaireUniteLegale": false,
          "caractereEmployeurUniteLegale": "N",
          "changementCaractereEmployeurUniteLegale": false
        }
      ]
    },
    {
      "siren": "812141125",
      "statutDiffusionUniteLegale": "O",
      "dateCreationUniteLegale": "2015-06-11",
      "sigleUniteLegale": "CMHM",
      "sexeUniteLegale": null,
      "prenom1UniteLegale": null,
      "prenom2UniteLegale": null,
      "prenom3UniteLegale": null,
      "prenom4UniteLegale": null,
      "prenomUsuelUniteLegale": null,
      "pseudonymeUniteLegale": null,
      "identifiantAssociationUniteLegale": null,
      "trancheEffectifsUniteLegale": null,
      "anneeEffectifsUniteLegale": null,
      "dateDernierTraitementUniteLegale": "2017-06-12T14:25:21",
      "nombrePeriodesUniteLegale": 2,
      "categorieEntreprise": "PME",
      "anneeCategorieEntreprise": "2016",
      "periodesUniteLegale": [
        {
          "dateFin": null,
          "dateDebut": "2017-04-14",
          "etatAdministratifUniteLegale": "A",
          "changementEtatAdministratifUniteLegale": false,
          "nomUniteLegale": null,
          "changementNomUniteLegale": false,
          "nomUsageUniteLegale": null,
          "changementNomUsageUniteLegale": false,
          "denominationUniteLegale": "APS MULTI -SERVICES",
          "changementDenominationUniteLegale": true,
          "denominationUsuelle1UniteLegale": null,
          "denominationUsuelle2UniteLegale": null,
          "denominationUsuelle3UniteLegale": null,
          "changementDenominationUsuelleUniteLegale": false,
          "categorieJuridiqueUniteLegale": "5720",
          "changementCategorieJuridiqueUniteLegale": false,
          "activitePrincipaleUniteLegale": "46.73A",
          "nomenclatureActivitePrincipaleUniteLegale": "NAFRev2",
          "changementActivitePrincipaleUniteLegale": true,
          "nicSiegeUniteLegale": "00029",
          "changementNicSiegeUniteLegale": true,
          "economieSocialeSolidaireUniteLegale": null,
          "changementEconomieSocialeSolidaireUniteLegale": false,
          "caractereEmployeurUniteLegale": "N",
          "changementCaractereEmployeurUniteLegale": false
        },
        {
          "dateFin": "2017-04-13",
          "dateDebut": "2015-06-11",
          "etatAdministratifUniteLegale": "A",
          "changementEtatAdministratifUniteLegale": false,
          "nomUniteLegale": null,
          "changementNomUniteLegale": false,
          "nomUsageUniteLegale": null,
          "changementNomUsageUniteLegale": false,
          "denominationUniteLegale": "COMPAGNIE MINIERE DU HAUT MARONI",
          "changementDenominationUniteLegale": false,
          "denominationUsuelle1UniteLegale": null,
          "denominationUsuelle2UniteLegale": null,
          "denominationUsuelle3UniteLegale": null,
          "changementDenominationUsuelleUniteLegale": false,
          "categorieJuridiqueUniteLegale": "5720",
          "changementCategorieJuridiqueUniteLegale": false,
          "activitePrincipaleUniteLegale": "07.29Z",
          "nomenclatureActivitePrincipaleUniteLegale": "NAFRev2",
          "changementActivitePrincipaleUniteLegale": false,
          "nicSiegeUniteLegale": "00011",
          "changementNicSiegeUniteLegale": false,
          "economieSocialeSolidaireUniteLegale": null,
          "changementEconomieSocialeSolidaireUniteLegale": false,
          "caractereEmployeurUniteLegale": "N",
          "changementCaractereEmployeurUniteLegale": false
        }
      ]
    },
    {
      "siren": "804906105",
      "statutDiffusionUniteLegale": "O",
      "dateCreationUniteLegale": "2014-10-01",
      "sigleUniteLegale": null,
      "sexeUniteLegale": null,
      "prenom1UniteLegale": null,
      "prenom2UniteLegale": null,
      "prenom3UniteLegale": null,
      "prenom4UniteLegale": null,
      "prenomUsuelUniteLegale": null,
      "pseudonymeUniteLegale": null,
      "identifiantAssociationUniteLegale": null,
      "trancheEffectifsUniteLegale": null,
      "anneeEffectifsUniteLegale": null,
      "dateDernierTraitementUniteLegale": "2017-05-20T04:20:05",
      "nombrePeriodesUniteLegale": 1,
      "categorieEntreprise": "PME",
      "anneeCategorieEntreprise": "2016",
      "periodesUniteLegale": [
        {
          "dateFin": null,
          "dateDebut": "2014-10-01",
          "etatAdministratifUniteLegale": "A",
          "changementEtatAdministratifUniteLegale": false,
          "nomUniteLegale": null,
          "changementNomUniteLegale": false,
          "nomUsageUniteLegale": null,
          "changementNomUsageUniteLegale": false,
          "denominationUniteLegale": "GIGAMINES",
          "changementDenominationUniteLegale": false,
          "denominationUsuelle1UniteLegale": null,
          "denominationUsuelle2UniteLegale": null,
          "denominationUsuelle3UniteLegale": null,
          "changementDenominationUsuelleUniteLegale": false,
          "categorieJuridiqueUniteLegale": "5499",
          "changementCategorieJuridiqueUniteLegale": false,
          "activitePrincipaleUniteLegale": "07.29Z",
          "nomenclatureActivitePrincipaleUniteLegale": "NAFRev2",
          "changementActivitePrincipaleUniteLegale": false,
          "nicSiegeUniteLegale": "00015",
          "changementNicSiegeUniteLegale": false,
          "economieSocialeSolidaireUniteLegale": null,
          "changementEconomieSocialeSolidaireUniteLegale": false,
          "caractereEmployeurUniteLegale": "N",
          "changementCaractereEmployeurUniteLegale": false
        }
      ]
    },
    {
      "siren": "814103982",
      "statutDiffusionUniteLegale": "O",
      "dateCreationUniteLegale": "2015-10-15",
      "sigleUniteLegale": null,
      "sexeUniteLegale": null,
      "prenom1UniteLegale": null,
      "prenom2UniteLegale": null,
      "prenom3UniteLegale": null,
      "prenom4UniteLegale": null,
      "prenomUsuelUniteLegale": null,
      "pseudonymeUniteLegale": null,
      "identifiantAssociationUniteLegale": null,
      "trancheEffectifsUniteLegale": null,
      "anneeEffectifsUniteLegale": null,
      "dateDernierTraitementUniteLegale": "2017-09-07T13:59:22",
      "nombrePeriodesUniteLegale": 2,
      "categorieEntreprise": "PME",
      "anneeCategorieEntreprise": "2016",
      "periodesUniteLegale": [
        {
          "dateFin": null,
          "dateDebut": "2017-07-27",
          "etatAdministratifUniteLegale": "A",
          "changementEtatAdministratifUniteLegale": false,
          "nomUniteLegale": null,
          "changementNomUniteLegale": false,
          "nomUsageUniteLegale": null,
          "changementNomUsageUniteLegale": false,
          "denominationUniteLegale": "J.E MINERATION",
          "changementDenominationUniteLegale": false,
          "denominationUsuelle1UniteLegale": null,
          "denominationUsuelle2UniteLegale": null,
          "denominationUsuelle3UniteLegale": null,
          "changementDenominationUsuelleUniteLegale": false,
          "categorieJuridiqueUniteLegale": "5710",
          "changementCategorieJuridiqueUniteLegale": false,
          "activitePrincipaleUniteLegale": "07.29Z",
          "nomenclatureActivitePrincipaleUniteLegale": "NAFRev2",
          "changementActivitePrincipaleUniteLegale": false,
          "nicSiegeUniteLegale": "00025",
          "changementNicSiegeUniteLegale": true,
          "economieSocialeSolidaireUniteLegale": null,
          "changementEconomieSocialeSolidaireUniteLegale": false,
          "caractereEmployeurUniteLegale": "N",
          "changementCaractereEmployeurUniteLegale": false
        },
        {
          "dateFin": "2017-07-26",
          "dateDebut": "2015-10-15",
          "etatAdministratifUniteLegale": "A",
          "changementEtatAdministratifUniteLegale": false,
          "nomUniteLegale": null,
          "changementNomUniteLegale": false,
          "nomUsageUniteLegale": null,
          "changementNomUsageUniteLegale": false,
          "denominationUniteLegale": "J.E MINERATION",
          "changementDenominationUniteLegale": false,
          "denominationUsuelle1UniteLegale": null,
          "denominationUsuelle2UniteLegale": null,
          "denominationUsuelle3UniteLegale": null,
          "changementDenominationUsuelleUniteLegale": false,
          "categorieJuridiqueUniteLegale": "5710",
          "changementCategorieJuridiqueUniteLegale": false,
          "activitePrincipaleUniteLegale": "07.29Z",
          "nomenclatureActivitePrincipaleUniteLegale": "NAFRev2",
          "changementActivitePrincipaleUniteLegale": false,
          "nicSiegeUniteLegale": "00017",
          "changementNicSiegeUniteLegale": false,
          "economieSocialeSolidaireUniteLegale": null,
          "changementEconomieSocialeSolidaireUniteLegale": false,
          "caractereEmployeurUniteLegale": "N",
          "changementCaractereEmployeurUniteLegale": false
        }
      ]
    },
    {
      "siren": "811348200",
      "statutDiffusionUniteLegale": "O",
      "dateCreationUniteLegale": "2015-03-23",
      "sigleUniteLegale": null,
      "sexeUniteLegale": null,
      "prenom1UniteLegale": null,
      "prenom2UniteLegale": null,
      "prenom3UniteLegale": null,
      "prenom4UniteLegale": null,
      "prenomUsuelUniteLegale": null,
      "pseudonymeUniteLegale": null,
      "identifiantAssociationUniteLegale": null,
      "trancheEffectifsUniteLegale": "00",
      "anneeEffectifsUniteLegale": "2016",
      "dateDernierTraitementUniteLegale": "2018-09-29T13:52:22",
      "nombrePeriodesUniteLegale": 2,
      "categorieEntreprise": "PME",
      "anneeCategorieEntreprise": "2016",
      "periodesUniteLegale": [
        {
          "dateFin": null,
          "dateDebut": "2015-09-01",
          "etatAdministratifUniteLegale": "A",
          "changementEtatAdministratifUniteLegale": false,
          "nomUniteLegale": null,
          "changementNomUniteLegale": false,
          "nomUsageUniteLegale": null,
          "changementNomUsageUniteLegale": false,
          "denominationUniteLegale": "SOCIETE MINIERE TORRES",
          "changementDenominationUniteLegale": false,
          "denominationUsuelle1UniteLegale": null,
          "denominationUsuelle2UniteLegale": null,
          "denominationUsuelle3UniteLegale": null,
          "changementDenominationUsuelleUniteLegale": false,
          "categorieJuridiqueUniteLegale": "5499",
          "changementCategorieJuridiqueUniteLegale": false,
          "activitePrincipaleUniteLegale": "07.29Z",
          "nomenclatureActivitePrincipaleUniteLegale": "NAFRev2",
          "changementActivitePrincipaleUniteLegale": false,
          "nicSiegeUniteLegale": "00015",
          "changementNicSiegeUniteLegale": false,
          "economieSocialeSolidaireUniteLegale": null,
          "changementEconomieSocialeSolidaireUniteLegale": false,
          "caractereEmployeurUniteLegale": "O",
          "changementCaractereEmployeurUniteLegale": true
        },
        {
          "dateFin": "2015-08-31",
          "dateDebut": "2015-03-23",
          "etatAdministratifUniteLegale": "A",
          "changementEtatAdministratifUniteLegale": false,
          "nomUniteLegale": null,
          "changementNomUniteLegale": false,
          "nomUsageUniteLegale": null,
          "changementNomUsageUniteLegale": false,
          "denominationUniteLegale": "SOCIETE MINIERE TORRES",
          "changementDenominationUniteLegale": false,
          "denominationUsuelle1UniteLegale": null,
          "denominationUsuelle2UniteLegale": null,
          "denominationUsuelle3UniteLegale": null,
          "changementDenominationUsuelleUniteLegale": false,
          "categorieJuridiqueUniteLegale": "5499",
          "changementCategorieJuridiqueUniteLegale": false,
          "activitePrincipaleUniteLegale": "07.29Z",
          "nomenclatureActivitePrincipaleUniteLegale": "NAFRev2",
          "changementActivitePrincipaleUniteLegale": false,
          "nicSiegeUniteLegale": "00015",
          "changementNicSiegeUniteLegale": false,
          "economieSocialeSolidaireUniteLegale": null,
          "changementEconomieSocialeSolidaireUniteLegale": false,
          "caractereEmployeurUniteLegale": "N",
          "changementCaractereEmployeurUniteLegale": false
        }
      ]
    },
    {
      "siren": "804686582",
      "statutDiffusionUniteLegale": "O",
      "dateCreationUniteLegale": "2014-09-04",
      "sigleUniteLegale": null,
      "sexeUniteLegale": null,
      "prenom1UniteLegale": null,
      "prenom2UniteLegale": null,
      "prenom3UniteLegale": null,
      "prenom4UniteLegale": null,
      "prenomUsuelUniteLegale": null,
      "pseudonymeUniteLegale": null,
      "identifiantAssociationUniteLegale": null,
      "trancheEffectifsUniteLegale": null,
      "anneeEffectifsUniteLegale": null,
      "dateDernierTraitementUniteLegale": "2017-05-20T04:18:50",
      "nombrePeriodesUniteLegale": 1,
      "categorieEntreprise": "PME",
      "anneeCategorieEntreprise": "2016",
      "periodesUniteLegale": [
        {
          "dateFin": null,
          "dateDebut": "2014-09-04",
          "etatAdministratifUniteLegale": "A",
          "changementEtatAdministratifUniteLegale": false,
          "nomUniteLegale": null,
          "changementNomUniteLegale": false,
          "nomUsageUniteLegale": null,
          "changementNomUsageUniteLegale": false,
          "denominationUniteLegale": "SGZ FRANCE SAS",
          "changementDenominationUniteLegale": false,
          "denominationUsuelle1UniteLegale": null,
          "denominationUsuelle2UniteLegale": null,
          "denominationUsuelle3UniteLegale": null,
          "changementDenominationUsuelleUniteLegale": false,
          "categorieJuridiqueUniteLegale": "5720",
          "changementCategorieJuridiqueUniteLegale": false,
          "activitePrincipaleUniteLegale": "08.91Z",
          "nomenclatureActivitePrincipaleUniteLegale": "NAFRev2",
          "changementActivitePrincipaleUniteLegale": false,
          "nicSiegeUniteLegale": "00011",
          "changementNicSiegeUniteLegale": false,
          "economieSocialeSolidaireUniteLegale": null,
          "changementEconomieSocialeSolidaireUniteLegale": false,
          "caractereEmployeurUniteLegale": "N",
          "changementCaractereEmployeurUniteLegale": false
        }
      ]
    },
    {
      "siren": "803949650",
      "statutDiffusionUniteLegale": "O",
      "dateCreationUniteLegale": "2014-09-01",
      "sigleUniteLegale": null,
      "sexeUniteLegale": null,
      "prenom1UniteLegale": null,
      "prenom2UniteLegale": null,
      "prenom3UniteLegale": null,
      "prenom4UniteLegale": null,
      "prenomUsuelUniteLegale": null,
      "pseudonymeUniteLegale": null,
      "identifiantAssociationUniteLegale": null,
      "trancheEffectifsUniteLegale": "01",
      "anneeEffectifsUniteLegale": "2016",
      "dateDernierTraitementUniteLegale": "2018-09-29T13:43:50",
      "nombrePeriodesUniteLegale": 2,
      "categorieEntreprise": "PME",
      "anneeCategorieEntreprise": "2016",
      "periodesUniteLegale": [
        {
          "dateFin": null,
          "dateDebut": "2016-01-01",
          "etatAdministratifUniteLegale": "A",
          "changementEtatAdministratifUniteLegale": false,
          "nomUniteLegale": null,
          "changementNomUniteLegale": false,
          "nomUsageUniteLegale": null,
          "changementNomUsageUniteLegale": false,
          "denominationUniteLegale": "TRANSPORTS VILLETTE",
          "changementDenominationUniteLegale": false,
          "denominationUsuelle1UniteLegale": null,
          "denominationUsuelle2UniteLegale": null,
          "denominationUsuelle3UniteLegale": null,
          "changementDenominationUsuelleUniteLegale": false,
          "categorieJuridiqueUniteLegale": "5720",
          "changementCategorieJuridiqueUniteLegale": false,
          "activitePrincipaleUniteLegale": "49.41A",
          "nomenclatureActivitePrincipaleUniteLegale": "NAFRev2",
          "changementActivitePrincipaleUniteLegale": false,
          "nicSiegeUniteLegale": "00011",
          "changementNicSiegeUniteLegale": false,
          "economieSocialeSolidaireUniteLegale": null,
          "changementEconomieSocialeSolidaireUniteLegale": false,
          "caractereEmployeurUniteLegale": "O",
          "changementCaractereEmployeurUniteLegale": true
        },
        {
          "dateFin": "2015-12-31",
          "dateDebut": "2014-09-01",
          "etatAdministratifUniteLegale": "A",
          "changementEtatAdministratifUniteLegale": false,
          "nomUniteLegale": null,
          "changementNomUniteLegale": false,
          "nomUsageUniteLegale": null,
          "changementNomUsageUniteLegale": false,
          "denominationUniteLegale": "TRANSPORTS VILLETTE",
          "changementDenominationUniteLegale": false,
          "denominationUsuelle1UniteLegale": null,
          "denominationUsuelle2UniteLegale": null,
          "denominationUsuelle3UniteLegale": null,
          "changementDenominationUsuelleUniteLegale": false,
          "categorieJuridiqueUniteLegale": "5720",
          "changementCategorieJuridiqueUniteLegale": false,
          "activitePrincipaleUniteLegale": "49.41A",
          "nomenclatureActivitePrincipaleUniteLegale": "NAFRev2",
          "changementActivitePrincipaleUniteLegale": false,
          "nicSiegeUniteLegale": "00011",
          "changementNicSiegeUniteLegale": false,
          "economieSocialeSolidaireUniteLegale": null,
          "changementEconomieSocialeSolidaireUniteLegale": false,
          "caractereEmployeurUniteLegale": "N",
          "changementCaractereEmployeurUniteLegale": false
        }
      ]
    },
    {
      "siren": "813079365",
      "statutDiffusionUniteLegale": "O",
      "dateCreationUniteLegale": "2015-08-01",
      "sigleUniteLegale": "M3C SARL",
      "sexeUniteLegale": null,
      "prenom1UniteLegale": null,
      "prenom2UniteLegale": null,
      "prenom3UniteLegale": null,
      "prenom4UniteLegale": null,
      "prenomUsuelUniteLegale": null,
      "pseudonymeUniteLegale": null,
      "identifiantAssociationUniteLegale": null,
      "trancheEffectifsUniteLegale": null,
      "anneeEffectifsUniteLegale": null,
      "dateDernierTraitementUniteLegale": "2017-10-05T19:47:19",
      "nombrePeriodesUniteLegale": 2,
      "categorieEntreprise": "PME",
      "anneeCategorieEntreprise": "2016",
      "periodesUniteLegale": [
        {
          "dateFin": null,
          "dateDebut": "2017-09-18",
          "etatAdministratifUniteLegale": "A",
          "changementEtatAdministratifUniteLegale": false,
          "nomUniteLegale": null,
          "changementNomUniteLegale": false,
          "nomUsageUniteLegale": null,
          "changementNomUsageUniteLegale": false,
          "denominationUniteLegale": "MINES 3C SARL",
          "changementDenominationUniteLegale": false,
          "denominationUsuelle1UniteLegale": null,
          "denominationUsuelle2UniteLegale": null,
          "denominationUsuelle3UniteLegale": null,
          "changementDenominationUsuelleUniteLegale": false,
          "categorieJuridiqueUniteLegale": "5499",
          "changementCategorieJuridiqueUniteLegale": false,
          "activitePrincipaleUniteLegale": "07.29Z",
          "nomenclatureActivitePrincipaleUniteLegale": "NAFRev2",
          "changementActivitePrincipaleUniteLegale": false,
          "nicSiegeUniteLegale": "00017",
          "changementNicSiegeUniteLegale": false,
          "economieSocialeSolidaireUniteLegale": null,
          "changementEconomieSocialeSolidaireUniteLegale": false,
          "caractereEmployeurUniteLegale": "O",
          "changementCaractereEmployeurUniteLegale": true
        },
        {
          "dateFin": "2017-09-17",
          "dateDebut": "2015-08-01",
          "etatAdministratifUniteLegale": "A",
          "changementEtatAdministratifUniteLegale": false,
          "nomUniteLegale": null,
          "changementNomUniteLegale": false,
          "nomUsageUniteLegale": null,
          "changementNomUsageUniteLegale": false,
          "denominationUniteLegale": "MINES 3C SARL",
          "changementDenominationUniteLegale": false,
          "denominationUsuelle1UniteLegale": null,
          "denominationUsuelle2UniteLegale": null,
          "denominationUsuelle3UniteLegale": null,
          "changementDenominationUsuelleUniteLegale": false,
          "categorieJuridiqueUniteLegale": "5499",
          "changementCategorieJuridiqueUniteLegale": false,
          "activitePrincipaleUniteLegale": "07.29Z",
          "nomenclatureActivitePrincipaleUniteLegale": "NAFRev2",
          "changementActivitePrincipaleUniteLegale": false,
          "nicSiegeUniteLegale": "00017",
          "changementNicSiegeUniteLegale": false,
          "economieSocialeSolidaireUniteLegale": null,
          "changementEconomieSocialeSolidaireUniteLegale": false,
          "caractereEmployeurUniteLegale": "N",
          "changementCaractereEmployeurUniteLegale": false
        }
      ]
    }
  ]
}