{
  "type": "FeatureCollection",
  "features": [
    {
      "type": "Feature",
      "geometry": {
        "type": "Point",
        "coordinates": [
          1.91084599495,
          47.9002532959
        ]
      },
      "properties": {
        "id": "prefecture-45234-01",
        "codeInsee": "45234",
        "pivotLocal": "prefecture",
        "nom": "Préfecture - Loiret",
        "adresses": [
          {
            "type": "géopostale",
            "lignes": [
              "181, rue de Bourgogne"
            ],
            "codePostal": "45042",
            "commune": "Orléans Cedex 1",
            "coordonnees": [
              1.91084599495,
              47.9002532959
            ]
          }
        ],
        "horaires": [
          {
            "du": "lundi",
            "au": "vendredi",
            "heures": [
              {
                "de": "08:30:00",
                "a": "16:30:00"
              }
            ]
          }
        ],
        "email": "http://www.loiret.gouv.fr/Contactez-nous",
        "telephone": "0821 80 30 45",
        "url": "http://www.loiret.gouv.fr"
      }
    }
  ]
}